carboncue_sdk/__init__.py
carboncue_sdk/client.py
carboncue_sdk/config.py
carboncue_sdk/exceptions.py
carboncue_sdk/models.py
carboncue_sdk/region_mapper.py
carboncue_sdk-1.1.0.dist-info/METADATA
carboncue_sdk-1.1.0.dist-info/WHEEL
carboncue_sdk-1.1.0.dist-info/RECORD
