Metadata-Version: 2.4
Name: carboncue-sdk
Version: 1.1.0
Summary: Core SDK for carbon-aware computing
License: MIT
Requires-Python: >=3.11
Requires-Dist: httpx>=0.28.1
Requires-Dist: pydantic-settings>=2.7.1
Requires-Dist: pydantic>=2.10.5
Requires-Dist: python-dotenv>=1.0.1
Provides-Extra: dev
Requires-Dist: pytest-asyncio>=0.25.2; extra == 'dev'
Requires-Dist: pytest-mock>=3.14.0; extra == 'dev'
Requires-Dist: pytest>=8.3.4; extra == 'dev'
